[
  {
    "id": 1784818974835,
    "title": "《寂静岭2 Re》简评",
    "content": "## 简述：\n> *在久远的2001年9月24日，《寂静岭2》在PS2上发售，与世人见面。\n  而在21年后的2022年10.20，紧紧攥着SH系列不放的科乐美终于姗姗宣布了由Blooder Team外包制作的《寂静岭2RE》（以下简称《SH2RE》）。当然，我那时的想法是科乐美发动了魔法卡复活墓地里的科乐美之母，对于这份重制仍然保持观望的态度。\n  10.8日《SH2RE》正式解锁发售，两年后的今日（写于10.20），当完整的体验完整个一周目和1/4个二周目后，我可以说，Blooder Team制作的《SH2RE》绝对是尊重原作，富有诚意，尽力用此时代技术再现原作魅力的优秀重制。优秀的画面建模，富有张力的人物，怪物与剧情，无一不在展现这部游戏的美。所以本期的简评，给各位聊聊这部作品。*\n## 制作组\n  首先，我们来看看本次重制版的制作组， **Bloorder Team**。或许你还未曾听过这个制作组，但你一定听闻过这个游戏 **《层层惊恐》**。没错，正是Bloorder Team开发制作了这款优秀氛围感很足的恐怖游戏。此外，该组还制作了 **《观察者》《层层惊恐2》《灵媒》** 等恐怖类的游戏。\n  所以，我在22年听闻是由他们负责外包重制，至少放了半个心，至少一个深耕恐怖游戏的小制作组是知道怎么做恐怖游戏。而事实上在玩完整部《SH2RE》后，我也彻底对Bloorder Team放下了心，因为这次的重制既保留了原版的氛围，也做到了将PS2世代的画面、玩法现代化，同时也展现了他们的诚意。\n## 重点，重制版的改变\n### 1.画面\n  重制，重制，那首当其冲的，我们要聊的当然是画面建模的重制。那首先，《SH2》是于2001年PS2世代发布的作品，所以当时的无论是贴图质量还是模型面数精度，放在23年后的今天都是相当不够看的，所以重制最直观可以感受到的自然是画面光影。原作中的氛围感很大一部分来自于表世界浓厚的白雾，以及里世界的腐败腥恶。\n  先看**表世界**，首先《SH2》不是一个开放世界，而是一个箱庭，所以有足够的发挥空间去深入细致细节的表现，Bloorder Team(以下简称B.T)做的也是很棒。\n  首先原作中的白雾百分百的在重制版中得到了还原。其次，作为表世界的依旧是基于现实的寂静岭小镇，所以表现出这座被抛弃的小镇的破败是关键。而B.T的刻画也是很到位的，年久开裂的柏油路、源于雾气的斑驳水洼，被铁丝网拦住被木板封住的门窗，四处废弃的汽车以及每块玻璃上的灰尘污垢，这些细节串联起的街道外景都在无言的诉说这座小城早已被遗忘。当我们随着詹姆斯由卡兹街走入林边公寓，B.T同样为我们展现了优秀的还原和细节处理，斑驳污垢的地面，滴水潮湿的天花板，泡水开裂的壁面，以及破败蒙尘的家具，在昏暗光影的环境中，视域中也弥散着用于表现浊尘的粒子效果，你能明显感觉到这是一个被抛弃的破旧的楼宇，不会再有人在这里现身。\n  而当玩家第一次跨越那道艳色门扉来到蓝溪公寓后，**里世界**第一次展现在了玩家眼前，色调由之前灰暗已转为猩腐，墙面不断剥落露出里面的钢筋铁网，所处可见的血污腌臜、锈蚀斑痕，这里是潜意识的深层，是来到这里的人心结的具象化，B.T对场景的制作刻画也是将原作的张力再现的很到位。\n然后，我们再来看看怪物，重制版的怪物设计请来了原作设计者伊藤畅达亲自操刀，所以《SH2RE》对原作的怪物还原是分毫不差，更加精致的。\n ~~（而让我难过的是，三角头老公还是瘦了点，要是能再壮一点，然后凸显一下雄风，穿个一丝不挂围裙，我会真的走不动路，自愿让他砍的）~~\n### 2.音乐\n  看完画面，于画面相辅相成的自然是烘托表现氛围感的音乐，同样的，《SH2RE》请来了原作的作曲山冈晃负责重制。除了更高的音质、码率，重制音乐自然也是加入了新的曲调，新的音色。结合山冈晃自己的话，多年过去，当时的心境状态早已不在，但现在的重制音乐依旧是用心去创作诠释，去贴合游戏本身，所以《SH2RE》的音乐你与原版比较，会发现少了几分阴沉，因为新乐色，新曲调的加入，而多了几分希望。就比如最经典的《Promise》重制的新版，多了几分当你重回故地的怅然怀念、更有活力一些，而原版更多的则是遗憾渺茫，但无论如何，没有高低之分。\n  然后，我们再来看看用于烘托氛围的环境音。在开阔街道探索时的白噪音，以及当警报鸣笛响起时伴随之的风声，开阔场地的压抑氛围就表现得很出色。到了室内，比如布鲁克黑文医院，作为背景音，加入了粗粝的呼吸声作为白噪音，配合电梯故障的刮擦声、黑暗的环境，紧张的氛围也是迅速有效的铺展开来。而到了里世界，配合遍布的铁丝网，钢筋，背景音则变换为了类似工业嘈杂音、金属的刮擦声等，那种异常、不合常理的感觉也会油然而生。\n## 重点，重制版的改变\n### 3.剧情\n  接着来看看剧情的变化。首先，原作的剧情可以说是很相当出彩的，所以只要不是乱改，都不会差到哪里。自然B.T做的也是很棒，基本上所有故事都是利用现代的技术进行精细化，对于故事主体没有过多的调整，微微调整了一些角色的碰面地点和时间，最明显的是把艾迪和劳拉的碰面由原先的保龄球馆改为了歌剧院中，同时与三角头的一部分的遇见和互动也因迷题的调整也作出了改变。\n  对于人物的描摹，自然也是更加的精进。作为主角**詹姆斯**，在丧妻鳏夫的表现上，首先在面容上的表现相比原版，面部细节自然是更加的细节，胡子拉扎，深陷的眼窝笼着厚重的黑眼圈，略有半壁的眼皮以及空洞略带无神的双眸，你能更加深刻的从他身上感受到丧妻之痛以及在长期照料绝症折磨下的妻子的身心俱疲。在言语的表现方面，《SH2RE》中詹姆斯的声线同样加深了年龄的感觉，语调音高也偏向了低沉疲惫的感觉，相比原版冠幅气质更加的呈现。而**安吉拉、艾迪**在CG中的面容神态、肢体语言的表现也更加的传神，贴合他们的状态。**安吉拉**，在童年时遭遇无数来自父亲的家暴虐待而患抑郁和创伤后应激反应，原作就表现出的安吉拉前一秒稳定与下一秒的崩溃应激在重制版的CG中配合更细致的面部表情和动作也是更加的深入人心。而**艾迪**，因自己对于面容形体而自卑的，也在众人的嘲讽中变为一个受虐狂，而寂静岭放大了施虐者的他的嘲笑，让他也最终精神崩溃，CG中满是腌臜的安迪对于詹姆斯的问候指向性的恶意揣测，以戏谑地口吻嘲弄着意外身亡的npc尸体，那股精神失控的表现也是在重制版中得到了更加让我讨厌的表现。\n  最后，结局方面，除了原版就有的 **“在水中”“离开”“玛丽亚”“狗”“UFO”“重生”**，本作还新增了 **“极乐”“寂静”**，当然在过完结局后，搞笑结局“UFO”依旧是我最喜欢的结局，甚至意外的和原作联动在了一起。\n### 4.游戏的玩法\n  聊完的了看的观与闻的方面，接下来再来看看游戏玩法的变化，首先最直观的就是，原版《SH2》是**固定视角转动**，而《SH2RE》则改为了更加符合现代风格的**越肩视角**，更加符合现代的操作直觉。\n  玩法方面，由文本内容推进解密，层层递进故事的发展是B.T的长项，在《SH2RE》中，这项长处也是自然而然地得到了二发扬光大，首先是优化移动一部分原版的位置，使其能更加顺畅的融入一个大关卡的箱庭探索解密，同时解密的逻辑性，引导性做的也很出色，昂长重复的跑图的时间部分并不多，也间接地提高了游戏场景的利用率。另外，《SH2RE》的解密也根据难度进行了动态分配与一部分的随机生成，无论是揭秘苦手还是高玩都能顺畅享受有游戏的乐趣 **（10.24再编辑：实际上是三种难度三种密码，个别密码固定但随机顺序，利用穷举也是几分钟的事情，还有一部分是三种难度均一样）** 游戏中的26个浮光掠影收集就是在致敬改动前的原解密。\n  战斗方面，我玩过原版，原版的射击体验对我来是是有点难上手有点糟糕的，《SH2RE》因为改成了越肩视角，所以瞄准射击肯定是有大幅提升的，而且因为在辅助选项中有自瞄，所以我的体验多少是很不错的，然后在资源分配方面，看来B.T是生怕玩家爽不起来，即使是我二周目都是困难下，资源依旧是处于一个充足且有余裕的状态，这多少能让一部分胆小的玩家稍微放宽点心（恐惧来源于火力不足）。\n  最后提一下闪避，《SH2RE》的詹姆斯真的是闪避战神，人家的闪避判定略严苛，而詹姆斯呢，连前摇都带有无敌帧，整个闪避的无敌时间很长，所以你若还是个艾尔登之王，你可以尝试无伤自限仅近战武器通关。\n## 缺点\n  谈完了游戏的改进与优秀之处,那当然也需要戳戳他的肺管子。\n  首先吐槽，明明2001年的游戏作为剧情拓展的DLC已经是全出完了，要重制完全可以连带DLC一起重制。但可惜《SH2RE》只重制了本体，而属于玛丽亚的支线《因愿而生》却未被重制，这多少让人难过。\n  然后，来看游戏的表现的缺憾，首先是探索和战斗方面。詹姆斯在探索过程中的越过障碍的动作，可以说是基本没有衔接，很生硬，就比如匍匐并没有一个顺畅的蹲下再趴下的过程，而是刷的直接贴地上爬过去了。战斗，枪的体验还算不错，有问题的还是使用近战武器的体验的，挥动木棍（水管）的动作多少还是有点软绵绵的，而且打击的反馈做的也有点钝有点闷。当然，打击动作的多少还能用詹姆斯本来就是不是李三光类型的人，但打击反馈做的不好也是要说出来的，就算是小厂也一样。\n  接着来看看游戏最为诟病的一点，糟糕的优化。首先，原版的迷雾有一部分的原因就是碍于机能的受限加上的，所以说难听点一部分的原因就是为了遮丑。而到了《SH2RE》这迷雾不再是提升游戏性能的用物，反而因为是使用了大量的体积雾，反而导致了室外场面的帧数降低。\n  到了室内，因为不用渲染室外的场景，这里的帧数也会提高一些，但并不会提高太多，主要的原因则是因为更多的精细细节的渲染，而导致了压力增大，导致部分场景下的帧数不太稳定。另外，不得不吐槽的是，这个游戏的优化在**DX11**上的优化更好，以DX11启用游戏反而会比**DX12**高上**10帧**左右，这真的很让人哭笑不得，毕竟一般情况下，在DX12上的优化肯定是会比DX11更好一些的，而这游戏反过来。\n  最后，部分脸型的改变，即特指玛丽亚、安吉拉，明明看着艺术设定集里两位相当美的面容，结果一位到了游戏里像是大妈的感觉，一位没有完全展现出詹姆斯因愿而生的玛丽亚的美貌，我真的是恨透了所谓的“女性面容丑化是为了照顾女性感受”。\n  以及最难以接受的一个汉化问题，在文本查看时的提示“轻抛“，明明翻译为”翻转“才更合适，byd和《诸神黄昏》里的轻推“WASD”一起给我气笑了，哪怕稍微审一审，也忽略不了这么一个明显的译制错误。\n  以上是目前体验下来，很明显的不足之处，但怎么说呢，瑕不掩瑜，还能接受（除了烂优化）。\n## 结语\n> *整篇的文章，抠抠搜搜只写了5000字不到，因为去掉世界观和一些基础设定的介绍，所以篇幅是达不到当初写《2077》测评的字数了。但总的来说，这是一部很有诚意很游戏的重制版游戏，你能看见外包制作组对游戏的上心用心，他们尽力去把游戏用现代的技术表现了出来，游戏的画面，音乐，氛围塑造的都很棒。（因为我已经是那种完全吓不到的人了，玩恐怖游戏更多是在品味它是如何呈现恐怖的）从我的一位朋友（有点解密苦手）玩的时候心率上升，被吓到会虎躯一震的，又会被故事感染，也没有明显的卡关的表现来看，这是一部优秀的心理恐怖游戏。当然，我曾希望它能像《生化2RE》《死亡空间RE》一样能够成为超越原作的优秀重制，所以多少会有点惋惜。但这不妨碍我爱上这游戏，当《Promise》熟悉的旋律再次响起，我知道一切的游玩都是值得的，我仿佛就回到了7年前的那个暑假，半夜偷偷打电脑看着“玛丽亚”结局的CG出现，听见《Promise》在我耳中想起…所以sm科乐美快重制1代（7年前春节假期游玩）、3代（6年前暑假游玩）、4代（6年前国庆假期游玩）和起源（6年前寒假游玩），我要狠狠的看教会主线啊*",
    "format": "markdown",
    "tags": [
      "#游戏 #寂静岭2RE"
    ],
    "cover": "https://raw.githubusercontent.com/JarosKrenyd/JarosK.github.io/main/articles/covers/blog_1784818212223_silent-hill-2-remake-detonado-01-2048x1152.jpg",
    "coverPath": "articles/covers/blog_1784818212223_silent-hill-2-remake-detonado-01-2048x1152.jpg",
    "time": "2026-07-23T15:02:54.835Z",
    "updated": "2026-07-23T15:03:51.257Z"
  },
  {
    "id": 1784818053003,
    "title": "《Robot Dreams》讲述离别",
    "content": "## **简介：**\n> *一只孤独的小狗遇到了一个机器人，偌大的城市中，他们互相依靠，温暖彼此。然而一次意外让小狗和机器人遗憾错过，从此他们只能把对彼此的想念藏进梦中。只是，反复梦见的人，还会重逢吗？影片改编自Sara Varon的同名漫画。同时本片获得了第96届奥斯卡金像奖最佳动画长片提名，第36届欧洲电影奖最佳动画片和第38届西班牙戈雅奖最佳改编剧本。*\n\n## 1.剧情\n### （1）背景设定\n  故事的社会背景设定在了纽约这个有着将近三成移动人口的超大都市，而这座城市的市民们则使用了拟人化的动物（简称：兽人）；没有任何的违和感也很舒适，上一个让我有如此感受的人物设计是在22年的原创番剧 **《ODD TAXI》** 里。本作的时代背景则设置在了 **上世纪80年代**（因为双子塔还没被撞），同时在此基础上增设了不少超时代的元素，比如最明显的复古未来主义造型的机器人。当然，超前的机器人也是本作讲述的依托关键。\n### （2）两线叙事\n  本片的故事组成很简单，分为了主人公小狗Varon和第二主人公机器人Amica 2000的两条线的故事。\n  在故事开头，小狗Varon长期的处于一个独处的状态，一个人玩游戏，一个人吃饭，但当他无意中看到隔壁的两个人在一起嘻嘻笑笑其乐融融，心中的孤独感被放大了无限倍，于是他订购了电视广告里的机器人“Amica 2000”。故事在此刻流转，**电影开始**。\n  焦急的等待，Varon终于盼来了他的机器人。组装，启动，机器人接过他手里的可乐，他终于有了自己的的一个朋友Amica，他的世界仿佛有了光。与Amica一起逛街，一起去看街头演出，一起去公园滑轮，Varon的世界被改变了，直到去海边的那一天。\n  Varon与Amica来到海边度假，一日的畅玩，让两人都很尽兴，但当正要离开时，小狗发现Amica动不了了，也搬不走，无奈之下 Varon只能暂时先回去等待第二天。只是这一别便是无告之终，也是从这一刻开始，故事正式封分为了两条线开始叙事。\n#### I.Varon（小狗）线\n  分别后的第二日，Varon又火急火燎的回到了海滩，但等着他的只有被铁丝网拦住直到来年6.1才会再次开放的海滩，他尝试强挤进去但被保安赶走，他尝试向市政府申请但遭到拨回，他深夜剪短锁链强闯但被保安逮捕留下案底。心灰意冷的Varon只能写下便签备忘，然后强迫自己参加各种活动，认识新的朋友，但无论怎么参加，眼前浮现的都是他的身影。但当来年6.1Varon再次第一时间回到海滩，无论他怎么找都再也找不到Amica，极度悲伤的他只能再次回到了他的家，抱着残存的腿彻夜难眠，然后来到机器人商店祈求找到相同的型号，但是怎么也找不到只有一个半价出售的Pal Robot，于是Varon买下了它，一段新的故事开始了。\n#### II.Amica（机器人）线\n  Amica的故事主要以3个梦穿插在主叙事之中，第一个梦里，他梦见三只兔子救活他使他能够重回Varon的家，但当他醒来看见的只是三只兔子无情的砍掉了他的腿用来补上船的漏洞。第二个梦，他梦见自己完好的再次回到家，但这次他看见的却是Varon购买一样的机器人取代了他的位置，第三个梦，最别样的梦，梦里小雏菊们跳着踢踏舞，摆出小狗头像的造型，那是Amica对Varon的无限思念。冬去春至，Amica也在漫长的等待中也见证了一次小鸟从破壳到迁徙的历程作为小插曲。但当海滩开放的前夕，来了一位拾荒者，他把Amica拖走卖给了废品站，Amica没有等来Varon，却等来了自己被当作废铁摔得支离破碎的最后一眼。命运是不可测的，一只小浣熊机缘巧合下换来了Amica的残余部件，他修好了Amica，机器人也开启了他与小浣熊的新生活。\n  两人都开始了自己的新生活，如果没有那么一次毫无征兆的偶遇……\n\n## 2.画面，人物塑造\n  首先本篇的整体采用了**手绘2D**的制作，同时使用简约线条和柔和色彩，来表现轻松但又富有深意的故事。又同时本篇全程**没有台词**，所以通过色调的改变、镜头语言、表情的转变等一系列视觉语言来传达想要表达的思想感情。\n  对于社会人文的表现，从片中的诸多环境的刻画细节可以看到，一个优秀的群像塑造，每个人都在干着在这个地方这个时代应该干的事情，没有多余也没有刻意，一切都看着很自然很和谐，仿佛就在看着一个有动物构成的上世纪八十年代的纽约。\n  而人物的塑造，在没有了台词配合的场景下就显得格外重要，当然本片做的也自然出色，没有过多复杂的动作，都是流畅朴实的那些下意识就会做出的动作，很现实也很让人能够沉浸，而Varon、Amica、Pal和小浣熊Rascal的人物面容虽然简约，但每一次挑眼、微笑抑或是悲伤，这些表情的刻画幅度或许有一些夸张，但非常的真实也能很迅速的表现和传递出讯息。就像是在看着卓别林的默剧一样，虽然全程没有一句台词，但你能从一言一行中感知到所在发生的事，想要传达的情，及不多余也不缺乏，恰到好处。\n  再看一些细枝末节的处理，比如色调的转变：在本篇**11：45至14：25**，Varon与Amica的第一次迪斯科之舞的桥段中，本片在柔和的色彩中加入了更多的碰撞色彩，来表现Varon世界因有了朋友而明亮乐观的转变。而在本篇**70：00至75：20**，作为本片的一个情感低点，这一桥段蒙上了一层显而易见的灰色色调，来变现Varon又一次失去一个短暂认识的朋友、Amica被无情报废的低落和悲伤的情感。\n\n## 3.内核分析\n  小狗Varon与机器人Amica的分离或许在我们的上帝视角仍然有着很多的解决办法，即使那是上世纪八十年代，但如何解决问题并不是本片的重点。这部电影想要依托这场分离作为载体讲述的，是离别。这场离别，不是因为什么很具象化的原因，比如社会的阻碍、家庭的阻挠，没有，只是一场没有缘由的不告而别，甚至再这场告别前，依旧相信明天还会再见。\n### I.当离别时，各自会有什么表现？\n  依托小狗的形象，电影很朴实的表现了失去一方的阶段，当失去后的一小段时间内，我们就像小狗Varon一样相信着可以失而复得，想要用尽手段去挽回去追回，**但并不是每一样东西每一样事儿都是可以“失而复得的”**。当发现无法失而复得后，小狗尝试去寻找替代，在等待海滩开放时尝试去社交结识新朋友，在彻底绝望后企图找一个一样的相近的去替代。欲盖弥彰，终究只是让伤口更加发炎，让人回想起失去的身影。**那既然这样尝试放下这段关系，开启一段新的道路**，于是小狗购买了新机器人Pal Robot（Pal，英语，同样译为朋友），与他开启新的生活。而失去的另一方的表现，则依托在机器人Amica的梦中（另外，应该是有意为之的时，Amica在意大利语中译为朋友）。第一场梦他梦见的是自己仍然保有的一丝幻想，就像小狗一样相信还能重聚，这就宛如波峰曲线上顶值；第二场梦他梦见的是自己的忧虑与害怕，它害怕自己被取代被遗忘，而这就是波谷，另一个极端；而第三场梦里，雏菊们的舞蹈摆出Varon的样子，就像是Amica想要狠狠的记住小狗的样貌，他害怕自己忘记小狗，也知道小狗可能再也不会来找他。当Amica被小浣熊Rascal救回，他或许仍怀着能再次见到小狗见面，但他也有意无意的进入到了他的与小浣熊的新生活中。\n### II.当离别之后，再次相遇又该如何？\n  相遇不会因期许而必然发生，反而可能就在那猝不及防的平凡的一瞬。就像电影中，Amica在哪儿都偶遇不到Varon，偏偏是在阳台上的看一眼，看到了那个魂牵梦绕的你。冲下去，追上你，抓住你的肩膀，和你紧紧抱在一起，是的我们重逢了，但一旁的Pal伤心了，身后赶来的Rascal在期许着，这是Amica做的第四场也是最后一场梦。藉由Amica，**当再次相遇，我们彼此都有了新的生活，又何必闯进对方的世界；既然我们行同陌路，那就放下彼此，让彼此开心**。\n  但分别与重逢都突如其来，你我不能再聚，那么就让我为你送上一场盛大的告别。播放这首你我最爱的歌《September》，让我们再一次隔空共舞一曲。高潮的最后一段，Pal看到了Varon喜欢这首歌这段舞，拍起手与Varon一起跳了起来；天台上Amica牵着Rascal也同样跳起相同的舞蹈，就像看《爱乐之城》一样，我感觉到的是释怀，**既然失去已无法挽回，不如彻底放下，然后开始一段新的路途**。Pal和Rascal都传承了美好的回忆，并会让之以特殊的方式延续下去。虽然我们不在一起，但我们会过得更好。\n## 结语：\n> *这是一部平稳而又朴素的电影，朴素的2D卡通，朴素的内核探讨，与同年上映的其他大哥，它显得有些微小，但他值得一次专注的观赏，让导演向传达的东西顺其自然的随影片流入内心，共鸣，思考。*",
    "format": "markdown",
    "tags": [
      "#影评 #Robot Dreams"
    ],
    "cover": "https://raw.githubusercontent.com/JarosKrenyd/JarosK.github.io/main/articles/covers/blog_1784818035067______2026-07-23_224656.png",
    "coverPath": "articles/covers/blog_1784818035067______2026-07-23_224656.png",
    "time": "2026-07-23T14:47:33.003Z",
    "updated": "2026-07-23T14:48:27.373Z"
  }
]